LICENSE
MANIFEST.in
README.rst
setup.py
django_s3_storages_utils.egg-info/PKG-INFO
django_s3_storages_utils.egg-info/SOURCES.txt
django_s3_storages_utils.egg-info/dependency_links.txt
django_s3_storages_utils.egg-info/not-zip-safe
django_s3_storages_utils.egg-info/requires.txt
django_s3_storages_utils.egg-info/top_level.txt
s3storagesutils/__init__.py
s3storagesutils/backends.py
s3storagesutils/cached.py