Metadata-Version: 1.1
Name: django-s3-storages-utils
Version: 0.1.0
Summary: django-s3-storages-utils - Utilities for setting up s3 for use with django-storages
Home-page: https://github.com/ravenac95/django-s3-storages-utils
Author: Reuven V. Gonzales
Author-email: reuven@tobetter.us
License: MIT
Platform: Unix
Classifier: License :: OSI Approved :: MIT License
Classifier: Intended Audience :: Developers
Classifier: Programming Language :: Python
Classifier: Operating System :: POSIX
